{
  "runId": "refresh-weekly-20260706T111325169Z",
  "startedAt": "2026-07-06T11:13:25.169Z",
  "finishedAt": "2026-07-06T11:13:25.169Z",
  "cadence": "weekly",
  "domainsRun": [
    "autonomy",
    "benchmarks",
    "compute",
    "economics",
    "energy",
    "hardware",
    "jobs",
    "policy",
    "research",
    "safety",
    "sentiment"
  ],
  "sourcesOk": 26,
  "sourcesFailed": 0,
  "quarantinedSamples": 0,
  "deltaMonths": -9.382571,
  "bandWidthDays": 2800.0613440972224,
  "status": "ok"
}
